Metadata-Version: 2.1
Name: rhasspy-supervisor
Version: 0.1.2
Summary: UNKNOWN
Home-page: https://github.com/rhasspy/rhasspy-supervisor
Author: Michael Hansen
Author-email: hansen.mike@gmail.com
License: UNKNOWN
Platform: UNKNOWN
Classifier: Programming Language :: Python :: 3
Classifier: Programming Language :: Python :: 3.6
Classifier: Programming Language :: Python :: 3.7
Classifier: Programming Language :: Python :: 3.8
Classifier: License :: OSI Approved :: MIT License
